MoranKV/__init__.py
MoranKV/methods.py
MoranKV-1.0.8.dist-info/LICENSE.txt
MoranKV-1.0.8.dist-info/METADATA
MoranKV-1.0.8.dist-info/WHEEL
MoranKV-1.0.8.dist-info/top_level.txt
MoranKV-1.0.8.dist-info/RECORD
