Metadata-Version: 2.1
Name: MoranKV
Version: 1.0.8
Summary: ...
Author: Zeta AI
Author-email: zeta.ai.company@gmail.com
License: MIT
Requires-Python: >=3.7
License-File: LICENSE.txt
Requires-Dist: kivy
Requires-Dist: kivymd
Requires-Dist: darkdetect
Requires-Dist: screeninfo
Requires-Dist: pyperclip
Requires-Dist: Filhanterare
